testing.mysqld-1.4.0-py2.7-nspkg.pth
testing/mysqld.py
testing.mysqld-1.4.0.dist-info/DESCRIPTION.rst
testing.mysqld-1.4.0.dist-info/METADATA
testing.mysqld-1.4.0.dist-info/RECORD
testing.mysqld-1.4.0.dist-info/WHEEL
testing.mysqld-1.4.0.dist-info/metadata.json
testing.mysqld-1.4.0.dist-info/namespace_packages.txt
testing.mysqld-1.4.0.dist-info/top_level.txt
